Metadata-Version: 2.4
Name: yfinance-qpython
Version: 0.2.52
Summary: Download market data from Yahoo! Finance API
Home-page: https://qpypi.qpython.org/project/yfinance-qpython/
Author: The QPYPI Team
Author-email: qpypi@qpython.org
License: Apache
Keywords: pandas,yahoo finance,pandas datareader
Platform: any
Classifier: Intended Audience :: Developers
Classifier: Intended Audience :: Education
Classifier: Intended Audience :: Information Technology
Classifier: Intended Audience :: End Users/Desktop
Classifier: License :: OSI Approved :: Apache Software License
Classifier: Operating System :: Android
Classifier: Programming Language :: Python
Classifier: Programming Language :: Python :: 3.12
Classifier: Topic :: Software Development
License-File: LICENSE.txt
Requires-Dist: pandas-aipy
Requires-Dist: numpy-aipy
Requires-Dist: requests>=2.31
Requires-Dist: multitasking>=0.0.7
Requires-Dist: lxml-qpython
Requires-Dist: platformdirs>=2.0.0
Requires-Dist: pytz>=2022.5
Requires-Dist: frozendict>=2.3.4
Requires-Dist: peewee>=3.16.2
Requires-Dist: beautifulsoup4>=4.11.1
Requires-Dist: html5lib>=1.1
Provides-Extra: nospam
Requires-Dist: requests_cache>=1.0; extra == "nospam"
Requires-Dist: requests_ratelimiter>=0.3.1; extra == "nospam"
Provides-Extra: repair
Requires-Dist: scipy-aipy; extra == "repair"
Dynamic: author
Dynamic: author-email
Dynamic: classifier
Dynamic: description
Dynamic: description-content-type
Dynamic: home-page
Dynamic: keywords
Dynamic: license
Dynamic: license-file
Dynamic: platform
Dynamic: provides-extra
Dynamic: requires-dist
Dynamic: summary
